raccoonlab_tools/common/colorizer.py
raccoonlab_tools/common/device_manager.py
raccoonlab_tools/common/firmware_manager.py
raccoonlab_tools/common/node.py
raccoonlab_tools/common/protocol_parser.py
raccoonlab_tools/cyphal/fragments.py
raccoonlab_tools/cyphal/gnss.py
raccoonlab_tools/cyphal/topic.py
raccoonlab_tools/cyphal/utils.py
raccoonlab_tools/cyphal/service/actuator.py
raccoonlab_tools/cyphal/service/barometer.py
raccoonlab_tools/cyphal/service/crct.py
raccoonlab_tools/cyphal/service/gnss.py
raccoonlab_tools/cyphal/service/lights.py
raccoonlab_tools/cyphal/service/magnetometer.py
raccoonlab_tools/dronecan/global_node.py
raccoonlab_tools/dronecan/utils.py
raccoonlab_tools/scripts/common/check_protocol.py
raccoonlab_tools/scripts/common/get_info.py
raccoonlab_tools/scripts/common/upload_firmware.py
raccoonlab_tools/scripts/cyphal/test_specification.py
raccoonlab_tools/scripts/cyphal/ublox_center.py
raccoonlab_tools/scripts/dronecan/config.py
raccoonlab_tools/scripts/dronecan/get_params.py
raccoonlab_tools/scripts/dronecan/set_params.py
raccoonlab_tools/scripts/dronecan/test_circuit_status.py
raccoonlab_tools/scripts/dronecan/test_flash.py
raccoonlab_tools/scripts/dronecan/test_gps_mag_baro.py
raccoonlab_tools/scripts/dronecan/test_lights.py
raccoonlab_tools/scripts/dronecan/test_pmu_buzzer.py
raccoonlab_tools/scripts/dronecan/test_specification.py
raccoonlab_tools/scripts/dronecan/buzzer_tester/test_buzzer.py
raccoonlab_tools/scripts/dronecan/lights_tester/lights_tester.py
raccoonlab_tools/scripts/dronecan/pwm_tester/pwm_tester.py
raccoonlab_tools/scripts/dronecan/servo_tester/node_parser.py
raccoonlab_tools/scripts/dronecan/servo_tester/servo_tester.py
raccoonlab_tools/scripts/dronecan/sim_battery/sim_battery.py
raccoonlab_tools/scripts/rl_git_info/script.py
raccoonlab_tools/scripts/rl_monitor/script.py
raccoonlab_tools/scripts/rl_printer/script.py
raccoonlab_tools/scripts/stm32/build_cubeide.py
raccoonlab_tools/scripts/stm32/test_ioc.py
raccoonlab_tools-0.2.0.dist-info/LICENSE
raccoonlab_tools-0.2.0.dist-info/METADATA
raccoonlab_tools-0.2.0.dist-info/WHEEL
raccoonlab_tools-0.2.0.dist-info/entry_points.txt
raccoonlab_tools-0.2.0.dist-info/top_level.txt
raccoonlab_tools-0.2.0.dist-info/RECORD
