Metadata-Version: 2.1
Name: raccoonlab-tools
Version: 0.2.0
Summary: RaccoonLab tools
Author-email: Dmitry Ponomarev <PonomarevDA96@gmail.com>
Project-URL: Homepage, https://github.com/PonomarevDA/tools
Project-URL: Bug Tracker, https://github.com/PonomarevDA/tools/issues
Keywords: cyphal,dronecan,can
Classifier: Programming Language :: Python :: 3
Classifier: License :: OSI Approved :: MIT License
Classifier: Operating System :: OS Independent
Requires-Python: >=3.7
License-File: LICENSE
Requires-Dist: pyserial
Requires-Dist: python-can==4.3
Requires-Dist: pytest
